LICENSE.rst
README.rst
pyproject.toml
setup.py
dafpy/__init__.py
dafpy/adapters.py
dafpy/anndata_format.py
dafpy/concat.py
dafpy/copies.py
dafpy/data.py
dafpy/formats.py
dafpy/generic_functions.py
dafpy/generic_logging.py
dafpy/julia_import.py
dafpy/operations.py
dafpy/py.typed
dafpy/queries.py
dafpy/reconstruction.py
dafpy/storage_types.py
dafpy/views.py
dafpy.egg-info/PKG-INFO
dafpy.egg-info/SOURCES.txt
dafpy.egg-info/dependency_links.txt
dafpy.egg-info/requires.txt
dafpy.egg-info/top_level.txt
docs/conf.py
tests/__init__.py
tests/test_adapters.py
tests/test_anndata_format.py
tests/test_concat.py
tests/test_copies.py
tests/test_formats.py
tests/test_generic.py
tests/test_queries.py
tests/test_reconstruction.py
tests/test_views.py
tests/utilities.py