Metadata-Version: 2.1
Name: dafpy
Version: 0.1.1
Summary: Data in Axes in Formats
Author-email: Oren Ben-Kiki <oren@ben-kiki.org>
License: Copyright © 2024 Weizmann Institute of Science
Project-URL: Homepage, https://github.com/tanaylab/Daf.py
Project-URL: Bug Tracker, https://github.com/tanaylab/Daf.py/issues
Classifier: Development Status :: 3 - Alpha
Classifier: Programming Language :: Python :: 3
Classifier: License :: OSI Approved :: MIT License
Classifier: Operating System :: OS Independent
Requires-Python: >=3.10
License-File: LICENSE.rst
Requires-Dist: juliacall
Requires-Dist: numpy
Requires-Dist: pandas
Requires-Dist: scipy
Provides-Extra: dev
Requires-Dist: black; extra == "dev"
Requires-Dist: bumpversion; extra == "dev"
Requires-Dist: flake8; extra == "dev"
Requires-Dist: isort; extra == "dev"
Requires-Dist: mypy; extra == "dev"
Requires-Dist: mypy_extensions; extra == "dev"
Requires-Dist: pandas-stubs; extra == "dev"
Requires-Dist: pylint; extra == "dev"
Requires-Dist: pytest; extra == "dev"
Requires-Dist: pytest-cov; extra == "dev"
Requires-Dist: sphinx; extra == "dev"
Requires-Dist: sphinx_rtd_theme; extra == "dev"
Requires-Dist: twine; extra == "dev"
Provides-Extra: test
Requires-Dist: pytest; extra == "test"
Requires-Dist: pytest-cov; extra == "test"
